apistar_crud/__init__.py
apistar_crud/admin.py
apistar_crud/resource/__init__.py
apistar_crud/resource/base.py
apistar_crud/resource/peewee.py
apistar_crud/resource/sqlalchemy.py
apistar_crud/routes.py
apistar_crud/static/0ab54153eeeca0ce03978cc463b257f7.woff2
apistar_crud/static/0ab54153eeeca0ce03978cc463b257f7.woff2
apistar_crud/static/13db00b7a34fee4d819ab7f9838cc428.eot
apistar_crud/static/13db00b7a34fee4d819ab7f9838cc428.eot
apistar_crud/static/701ae6abd4719e9c2ada3535a497b341.eot
apistar_crud/static/701ae6abd4719e9c2ada3535a497b341.eot
apistar_crud/static/82f60bd0b94a1ed68b1e6e309ce2e8c3.svg
apistar_crud/static/82f60bd0b94a1ed68b1e6e309ce2e8c3.svg
apistar_crud/static/8e3c7f5520f5ae906c6cf6d7f3ddcd19.eot
apistar_crud/static/8e3c7f5520f5ae906c6cf6d7f3ddcd19.eot
apistar_crud/static/962a1bf31c081691065fe333d9fa8105.svg
apistar_crud/static/962a1bf31c081691065fe333d9fa8105.svg
apistar_crud/static/9c74e172f87984c48ddf5c8108cabe67.png
apistar_crud/static/9c74e172f87984c48ddf5c8108cabe67.png
apistar_crud/static/a046592bac8f2fd96e994733faf3858c.woff
apistar_crud/static/a046592bac8f2fd96e994733faf3858c.woff
apistar_crud/static/a1a749e89f578a49306ec2b055c073da.svg
apistar_crud/static/a1a749e89f578a49306ec2b055c073da.svg
apistar_crud/static/ad97afd3337e8cda302d10ff5a4026b8.ttf
apistar_crud/static/ad97afd3337e8cda302d10ff5a4026b8.ttf
apistar_crud/static/b87b9ba532ace76ae9f6edfe9f72ded2.ttf
apistar_crud/static/b87b9ba532ace76ae9f6edfe9f72ded2.ttf
apistar_crud/static/c5ebe0b32dc1b5cc449a76c4204d13bb.ttf
apistar_crud/static/c5ebe0b32dc1b5cc449a76c4204d13bb.ttf
apistar_crud/static/cd6c777f1945164224dee082abaea03a.woff2
apistar_crud/static/cd6c777f1945164224dee082abaea03a.woff2
apistar_crud/static/e8c322de9658cbeb8a774b6624167c2c.woff2
apistar_crud/static/e8c322de9658cbeb8a774b6624167c2c.woff2
apistar_crud/static/ef60a4f6c25ef7f39f2d25a748dbecfe.woff
apistar_crud/static/ef60a4f6c25ef7f39f2d25a748dbecfe.woff
apistar_crud/static/faff92145777a3cbaf8e7367b4807987.woff
apistar_crud-0.6.6.dist-info/LICENSE
apistar_crud-0.6.6.dist-info/WHEEL
apistar_crud-0.6.6.dist-info/METADATA
apistar_crud-0.6.6.dist-info/RECORD
